Tabalchi/__init__.py
Tabalchi/main.py
Tabalchi-0.0.9.dist-info/LICENSE
Tabalchi-0.0.9.dist-info/METADATA
Tabalchi-0.0.9.dist-info/WHEEL
Tabalchi-0.0.9.dist-info/top_level.txt
Tabalchi-0.0.9.dist-info/RECORD
