Metadata-Version: 2.1
Name: Tabalchi
Version: 0.0.9
Summary: Tabalchi: Parser and Generator for Indian Classical Music
Home-page: https://github.com/shreyanmitra/Tabalchi
Author: Shreyan Mitra
Keywords: music midi indian-music,audio-transcription
License-File: LICENSE
Requires-Dist: jsonschema
Requires-Dist: playsound
Requires-Dist: pydub
Requires-Dist: audio-effects
Requires-Dist: pyacoustid
Requires-Dist: pychromaprint
Requires-Dist: typing
Requires-Dist: pathlib
Requires-Dist: transformers
Requires-Dist: torch
Requires-Dist: fsspec
Requires-Dist: rich
